{"POST": {"inner_id": "POST", "outer_id": "\u0427\u0420", "desc": "\u0447\u0430\u0441\u0442\u044c \u0440\u0435\u0447\u0438", "parent": "\u2014"}, "NOUN": {"inner_id": "NOUN", "outer_id": "\u0421\u0423\u0429", "desc": "\u0438\u043c\u044f \u0441\u0443\u0449\u0435\u0441\u0442\u0432\u0438\u0442\u0435\u043b\u044c\u043d\u043e\u0435", "parent": "POST"}, "ADJF": {"inner_id": "ADJF", "outer_id": "\u041f\u0420\u0418\u041b", "desc": "\u0438\u043c\u044f \u043f\u0440\u0438\u043b\u0430\u0433\u0430\u0442\u0435\u043b\u044c\u043d\u043e\u0435 (\u043f\u043e\u043b\u043d\u043e\u0435)", "parent": "POST"}, "ADJS": {"inner_id": "ADJS", "outer_id": "\u041a\u0420_\u041f\u0420\u0418\u041b", "desc": "\u0438\u043c\u044f \u043f\u0440\u0438\u043b\u0430\u0433\u0430\u0442\u0435\u043b\u044c\u043d\u043e\u0435 (\u043a\u0440\u0430\u0442\u043a\u043e\u0435)", "parent": "POST"}, "COMP": {"inner_id": "COMP", "outer_id": "\u041a\u041e\u041c\u041f", "desc": "\u043a\u043e\u043c\u043f\u0430\u0440\u0430\u0442\u0438\u0432", "parent": "POST"}, "VERB": {"inner_id": "VERB", "outer_id": "\u0413\u041b", "desc": "\u0433\u043b\u0430\u0433\u043e\u043b (\u043b\u0438\u0447\u043d\u0430\u044f \u0444\u043e\u0440\u043c\u0430)", "parent": "POST"}, "INFN": {"inner_id": "INFN", "outer_id": "\u0418\u041d\u0424", "desc": "\u0433\u043b\u0430\u0433\u043e\u043b (\u0438\u043d\u0444\u0438\u043d\u0438\u0442\u0438\u0432)", "parent": "POST"}, "PRTF": {"inner_id": "PRTF", "outer_id": "\u041f\u0420\u0418\u0427", "desc": "\u043f\u0440\u0438\u0447\u0430\u0441\u0442\u0438\u0435 (\u043f\u043e\u043b\u043d\u043e\u0435)", "parent": "POST"}, "PRTS": {"inner_id": "PRTS", "outer_id": "\u041a\u0420_\u041f\u0420\u0418\u0427", "desc": "\u043f\u0440\u0438\u0447\u0430\u0441\u0442\u0438\u0435 (\u043a\u0440\u0430\u0442\u043a\u043e\u0435)", "parent": "POST"}, "GRND": {"inner_id": "GRND", "outer_id": "\u0414\u0415\u0415\u041f\u0420", "desc": "\u0434\u0435\u0435\u043f\u0440\u0438\u0447\u0430\u0441\u0442\u0438\u0435", "parent": "POST"}, "NUMR": {"inner_id": "NUMR", "outer_id": "\u0427\u0418\u0421\u041b", "desc": "\u0447\u0438\u0441\u043b\u0438\u0442\u0435\u043b\u044c\u043d\u043e\u0435", "parent": "POST"}, "ADVB": {"inner_id": "ADVB", "outer_id": "\u041d", "desc": "\u043d\u0430\u0440\u0435\u0447\u0438\u0435", "parent": "POST"}, "NPRO": {"inner_id": "NPRO", "outer_id": "\u041c\u0421", "desc": "\u043c\u0435\u0441\u0442\u043e\u0438\u043c\u0435\u043d\u0438\u0435-\u0441\u0443\u0449\u0435\u0441\u0442\u0432\u0438\u0442\u0435\u043b\u044c\u043d\u043e\u0435", "parent": "POST"}, "PRED": {"inner_id": "PRED", "outer_id": "\u041f\u0420\u0415\u0414\u041a", "desc": "\u043f\u0440\u0435\u0434\u0438\u043a\u0430\u0442\u0438\u0432", "parent": "POST"}, "PREP": {"inner_id": "PREP", "outer_id": "\u041f\u0420", "desc": "\u043f\u0440\u0435\u0434\u043b\u043e\u0433", "parent": "POST"}, "CONJ": {"inner_id": "CONJ", "outer_id": "\u0421\u041e\u042e\u0417", "desc": "\u0441\u043e\u044e\u0437", "parent": "POST"}, "PRCL": {"inner_id": "PRCL", "outer_id": "\u0427\u0410\u0421\u0422", "desc": "\u0447\u0430\u0441\u0442\u0438\u0446\u0430", "parent": "POST"}, "INTJ": {"inner_id": "INTJ", "outer_id": "\u041c\u0415\u0416\u0414", "desc": "\u043c\u0435\u0436\u0434\u043e\u043c\u0435\u0442\u0438\u0435", "parent": "POST"}, "ANim": {"inner_id": "ANim", "outer_id": "\u041e\u0434-\u043d\u0435\u043e\u0434", "desc": "\u043a\u0430\u0442\u0435\u0433\u043e\u0440\u0438\u044f \u043e\u0434\u0443\u0448\u0435\u0432\u043b\u0451\u043d\u043d\u043e\u0441\u0442\u0438", "parent": "\u2014"}, "anim": {"inner_id": "anim", "outer_id": "\u043e\u0434", "desc": "\u043e\u0434\u0443\u0448\u0435\u0432\u043b\u0451\u043d\u043d\u043e\u0435", "parent": "ANim"}, "inan": {"inner_id": "inan", "outer_id": "\u043d\u0435\u043e\u0434", "desc": "\u043d\u0435\u043e\u0434\u0443\u0448\u0435\u0432\u043b\u0451\u043d\u043d\u043e\u0435", "parent": "ANim"}, "GNdr": {"inner_id": "GNdr", "outer_id": "\u0445\u0440", "desc": "\u0440\u043e\u0434 / \u0440\u043e\u0434 \u043d\u0435 \u0432\u044b\u0440\u0430\u0436\u0435\u043d", "parent": "\u2014"}, "masc": {"inner_id": "masc", "outer_id": "\u043c\u0440", "desc": "\u043c\u0443\u0436\u0441\u043a\u043e\u0439 \u0440\u043e\u0434", "parent": "ms-f"}, "femn": {"inner_id": "femn", "outer_id": "\u0436\u0440", "desc": "\u0436\u0435\u043d\u0441\u043a\u0438\u0439 \u0440\u043e\u0434", "parent": "ms-f"}, "neut": {"inner_id": "neut", "outer_id": "\u0441\u0440", "desc": "\u0441\u0440\u0435\u0434\u043d\u0438\u0439 \u0440\u043e\u0434", "parent": "GNdr"}, "ms-f": {"inner_id": "ms-f", "outer_id": "\u043c\u0436", "desc": "\u043e\u0431\u0449\u0438\u0439 \u0440\u043e\u0434 (\u043c/\u0436)", "parent": "GNdr"}, "NMbr": {"inner_id": "NMbr", "outer_id": "\u0427\u0438\u0441\u043b\u043e", "desc": "\u0447\u0438\u0441\u043b\u043e", "parent": "\u2014"}, "sing": {"inner_id": "sing", "outer_id": "\u0435\u0434", "desc": "\u0435\u0434\u0438\u043d\u0441\u0442\u0432\u0435\u043d\u043d\u043e\u0435 \u0447\u0438\u0441\u043b\u043e", "parent": "NMbr"}, "plur": {"inner_id": "plur", "outer_id": "\u043c\u043d", "desc": "\u043c\u043d\u043e\u0436\u0435\u0441\u0442\u0432\u0435\u043d\u043d\u043e\u0435 \u0447\u0438\u0441\u043b\u043e", "parent": "NMbr"}, "Sgtm": {"inner_id": "Sgtm", "outer_id": "sg", "desc": "singularia tantum", "parent": "\u2014"}, "Pltm": {"inner_id": "Pltm", "outer_id": "pl", "desc": "pluralia tantum", "parent": "\u2014"}, "Fixd": {"inner_id": "Fixd", "outer_id": "0", "desc": "\u043d\u0435\u0438\u0437\u043c\u0435\u043d\u044f\u0435\u043c\u043e\u0435", "parent": "\u2014"}, "CAse": {"inner_id": "CAse", "outer_id": "\u041f\u0430\u0434\u0435\u0436", "desc": "\u043a\u0430\u0442\u0435\u0433\u043e\u0440\u0438\u044f \u043f\u0430\u0434\u0435\u0436\u0430", "parent": "\u2014"}, "nomn": {"inner_id": "nomn", "outer_id": "\u0438\u043c", "desc": "\u0438\u043c\u0435\u043d\u0438\u0442\u0435\u043b\u044c\u043d\u044b\u0439 \u043f\u0430\u0434\u0435\u0436", "parent": "CAse"}, "gent": {"inner_id": "gent", "outer_id": "\u0440\u0434", "desc": "\u0440\u043e\u0434\u0438\u0442\u0435\u043b\u044c\u043d\u044b\u0439 \u043f\u0430\u0434\u0435\u0436", "parent": "CAse"}, "datv": {"inner_id": "datv", "outer_id": "\u0434\u0442", "desc": "\u0434\u0430\u0442\u0435\u043b\u044c\u043d\u044b\u0439 \u043f\u0430\u0434\u0435\u0436", "parent": "CAse"}, "accs": {"inner_id": "accs", "outer_id": "\u0432\u043d", "desc": "\u0432\u0438\u043d\u0438\u0442\u0435\u043b\u044c\u043d\u044b\u0439 \u043f\u0430\u0434\u0435\u0436", "parent": "CAse"}, "ablt": {"inner_id": "ablt", "outer_id": "\u0442\u0432", "desc": "\u0442\u0432\u043e\u0440\u0438\u0442\u0435\u043b\u044c\u043d\u044b\u0439 \u043f\u0430\u0434\u0435\u0436", "parent": "CAse"}, "loct": {"inner_id": "loct", "outer_id": "\u043f\u0440", "desc": "\u043f\u0440\u0435\u0434\u043b\u043e\u0436\u043d\u044b\u0439 \u043f\u0430\u0434\u0435\u0436", "parent": "CAse"}, "voct": {"inner_id": "voct", "outer_id": "\u0437\u0432", "desc": "\u0437\u0432\u0430\u0442\u0435\u043b\u044c\u043d\u044b\u0439 \u043f\u0430\u0434\u0435\u0436", "parent": "nomn"}, "gen1": {"inner_id": "gen1", "outer_id": "\u0440\u04341", "desc": "\u043f\u0435\u0440\u0432\u044b\u0439 \u0440\u043e\u0434\u0438\u0442\u0435\u043b\u044c\u043d\u044b\u0439 \u043f\u0430\u0434\u0435\u0436", "parent": "gent"}, "gen2": {"inner_id": "gen2", "outer_id": "\u0440\u04342", "desc": "\u0432\u0442\u043e\u0440\u043e\u0439 \u0440\u043e\u0434\u0438\u0442\u0435\u043b\u044c\u043d\u044b\u0439 (\u0447\u0430\u0441\u0442\u0438\u0447\u043d\u044b\u0439) \u043f\u0430\u0434\u0435\u0436", "parent": "gent"}, "acc2": {"inner_id": "acc2", "outer_id": "\u0432\u043d2", "desc": "\u0432\u0442\u043e\u0440\u043e\u0439 \u0432\u0438\u043d\u0438\u0442\u0435\u043b\u044c\u043d\u044b\u0439 \u043f\u0430\u0434\u0435\u0436", "parent": "accs"}, "loc1": {"inner_id": "loc1", "outer_id": "\u043f\u04401", "desc": "\u043f\u0435\u0440\u0432\u044b\u0439 \u043f\u0440\u0435\u0434\u043b\u043e\u0436\u043d\u044b\u0439 \u043f\u0430\u0434\u0435\u0436", "parent": "loct"}, "loc2": {"inner_id": "loc2", "outer_id": "\u043f\u04402", "desc": "\u0432\u0442\u043e\u0440\u043e\u0439 \u043f\u0440\u0435\u0434\u043b\u043e\u0436\u043d\u044b\u0439 (\u043c\u0435\u0441\u0442\u043d\u044b\u0439) \u043f\u0430\u0434\u0435\u0436", "parent": "loct"}, "Abbr": {"inner_id": "Abbr", "outer_id": "\u0430\u0431\u0431\u0440", "desc": "\u0430\u0431\u0431\u0440\u0435\u0432\u0438\u0430\u0442\u0443\u0440\u0430", "parent": "\u2014"}, "Name": {"inner_id": "Name", "outer_id": "\u0438\u043c\u044f", "desc": "\u0438\u043c\u044f", "parent": "\u2014"}, "Surn": {"inner_id": "Surn", "outer_id": "\u0444\u0430\u043c", "desc": "\u0444\u0430\u043c\u0438\u043b\u0438\u044f", "parent": "\u2014"}, "Patr": {"inner_id": "Patr", "outer_id": "\u043e\u0442\u0447", "desc": "\u043e\u0442\u0447\u0435\u0441\u0442\u0432\u043e", "parent": "\u2014"}, "Geox": {"inner_id": "Geox", "outer_id": "\u0433\u0435\u043e", "desc": "\u0442\u043e\u043f\u043e\u043d\u0438\u043c", "parent": "\u2014"}, "Orgn": {"inner_id": "Orgn", "outer_id": "\u043e\u0440\u0433", "desc": "\u043e\u0440\u0433\u0430\u043d\u0438\u0437\u0430\u0446\u0438\u044f", "parent": "\u2014"}, "Trad": {"inner_id": "Trad", "outer_id": "tm", "desc": "\u0442\u043e\u0440\u0433\u043e\u0432\u0430\u044f \u043c\u0430\u0440\u043a\u0430", "parent": "\u2014"}, "Subx": {"inner_id": "Subx", "outer_id": "\u0441\u0443\u0431\u0441\u0442?", "desc": "\u0432\u043e\u0437\u043c\u043e\u0436\u043d\u0430 \u0441\u0443\u0431\u0441\u0442\u0430\u043d\u0442\u0438\u0432\u0430\u0446\u0438\u044f", "parent": "\u2014"}, "Supr": {"inner_id": "Supr", "outer_id": "\u043f\u0440\u0435\u0432\u043e\u0441\u0445", "desc": "\u043f\u0440\u0435\u0432\u043e\u0441\u0445\u043e\u0434\u043d\u0430\u044f \u0441\u0442\u0435\u043f\u0435\u043d\u044c", "parent": "\u2014"}, "Qual": {"inner_id": "Qual", "outer_id": "\u043a\u0430\u0447", "desc": "\u043a\u0430\u0447\u0435\u0441\u0442\u0432\u0435\u043d\u043d\u043e\u0435", "parent": "\u2014"}, "Apro": {"inner_id": "Apro", "outer_id": "\u043c\u0435\u0441\u0442-\u043f", "desc": "\u043c\u0435\u0441\u0442\u043e\u0438\u043c\u0435\u043d\u043d\u043e\u0435", "parent": "\u2014"}, "Anum": {"inner_id": "Anum", "outer_id": "\u0447\u0438\u0441\u043b-\u043f", "desc": "\u043f\u043e\u0440\u044f\u0434\u043a\u043e\u0432\u043e\u0435", "parent": "\u2014"}, "Poss": {"inner_id": "Poss", "outer_id": "\u043f\u0440\u0438\u0442\u044f\u0436", "desc": "\u043f\u0440\u0438\u0442\u044f\u0436\u0430\u0442\u0435\u043b\u044c\u043d\u043e\u0435", "parent": "\u2014"}, "V-ey": {"inner_id": "V-ey", "outer_id": "*\u0435\u044e", "desc": "\u0444\u043e\u0440\u043c\u0430 \u043d\u0430 -\u0435\u044e", "parent": "\u2014"}, "V-oy": {"inner_id": "V-oy", "outer_id": "*\u043e\u044e", "desc": "\u0444\u043e\u0440\u043c\u0430 \u043d\u0430 -\u043e\u044e", "parent": "\u2014"}, "Cmp2": {"inner_id": "Cmp2", "outer_id": "\u0441\u0440\u0430\u0432\u043d2", "desc": "\u0441\u0440\u0430\u0432\u043d\u0438\u0442\u0435\u043b\u044c\u043d\u0430\u044f \u0441\u0442\u0435\u043f\u0435\u043d\u044c \u043d\u0430 \u043f\u043e-", "parent": "\u2014"}, "V-ej": {"inner_id": "V-ej", "outer_id": "*\u0435\u0439", "desc": "\u0444\u043e\u0440\u043c\u0430 \u043a\u043e\u043c\u043f\u0430\u0440\u0430\u0442\u0438\u0432\u0430 \u043d\u0430 -\u0435\u0439", "parent": "\u2014"}, "ASpc": {"inner_id": "ASpc", "outer_id": "\u0412\u0438\u0434", "desc": "\u043a\u0430\u0442\u0435\u0433\u043e\u0440\u0438\u044f \u0432\u0438\u0434\u0430", "parent": "\u2014"}, "perf": {"inner_id": "perf", "outer_id": "\u0441\u043e\u0432", "desc": "\u0441\u043e\u0432\u0435\u0440\u0448\u0435\u043d\u043d\u044b\u0439 \u0432\u0438\u0434", "parent": "ASpc"}, "impf": {"inner_id": "impf", "outer_id": "\u043d\u0435\u0441\u043e\u0432", "desc": "\u043d\u0435\u0441\u043e\u0432\u0435\u0440\u0448\u0435\u043d\u043d\u044b\u0439 \u0432\u0438\u0434", "parent": "ASpc"}, "TRns": {"inner_id": "TRns", "outer_id": "\u041f\u0435\u0440\u0435\u0445", "desc": "\u043a\u0430\u0442\u0435\u0433\u043e\u0440\u0438\u044f \u043f\u0435\u0440\u0435\u0445\u043e\u0434\u043d\u043e\u0441\u0442\u0438", "parent": "\u2014"}, "tran": {"inner_id": "tran", "outer_id": "\u043f\u0435\u0440\u0435\u0445", "desc": "\u043f\u0435\u0440\u0435\u0445\u043e\u0434\u043d\u044b\u0439", "parent": "TRns"}, "intr": {"inner_id": "intr", "outer_id": "\u043d\u0435\u043f\u0435\u0440\u0435\u0445", "desc": "\u043d\u0435\u043f\u0435\u0440\u0435\u0445\u043e\u0434\u043d\u044b\u0439", "parent": "TRns"}, "Impe": {"inner_id": "Impe", "outer_id": "\u0431\u0435\u0437\u043b", "desc": "\u0431\u0435\u0437\u043b\u0438\u0447\u043d\u044b\u0439", "parent": "\u2014"}, "Impx": {"inner_id": "Impx", "outer_id": "\u0431\u0435\u0437\u043b?", "desc": "\u0432\u043e\u0437\u043c\u043e\u0436\u043d\u043e \u0431\u0435\u0437\u043b\u0438\u0447\u043d\u043e\u0435 \u0443\u043f\u043e\u0442\u0440\u0435\u0431\u043b\u0435\u043d\u0438\u0435", "parent": "\u2014"}, "Mult": {"inner_id": "Mult", "outer_id": "\u043c\u043d\u043e\u0433", "desc": "\u043c\u043d\u043e\u0433\u043e\u043a\u0440\u0430\u0442\u043d\u044b\u0439", "parent": "\u2014"}, "Refl": {"inner_id": "Refl", "outer_id": "\u0432\u043e\u0437\u0432\u0440", "desc": "\u0432\u043e\u0437\u0432\u0440\u0430\u0442\u043d\u044b\u0439", "parent": "\u2014"}, "PErs": {"inner_id": "PErs", "outer_id": "\u041b\u0438\u0446\u043e", "desc": "\u043a\u0430\u0442\u0435\u0433\u043e\u0440\u0438\u044f \u043b\u0438\u0446\u0430", "parent": "\u2014"}, "1per": {"inner_id": "1per", "outer_id": "1\u043b", "desc": "1 \u043b\u0438\u0446\u043e", "parent": "PErs"}, "2per": {"inner_id": "2per", "outer_id": "2\u043b", "desc": "2 \u043b\u0438\u0446\u043e", "parent": "PErs"}, "3per": {"inner_id": "3per", "outer_id": "3\u043b", "desc": "3 \u043b\u0438\u0446\u043e", "parent": "PErs"}, "TEns": {"inner_id": "TEns", "outer_id": "\u0412\u0440\u0435\u043c\u044f", "desc": "\u043a\u0430\u0442\u0435\u0433\u043e\u0440\u0438\u044f \u0432\u0440\u0435\u043c\u0435\u043d\u0438", "parent": "\u2014"}, "pres": {"inner_id": "pres", "outer_id": "\u043d\u0430\u0441\u0442", "desc": "\u043d\u0430\u0441\u0442\u043e\u044f\u0449\u0435\u0435 \u0432\u0440\u0435\u043c\u044f", "parent": "TEns"}, "past": {"inner_id": "past", "outer_id": "\u043f\u0440\u043e\u0448", "desc": "\u043f\u0440\u043e\u0448\u0435\u0434\u0448\u0435\u0435 \u0432\u0440\u0435\u043c\u044f", "parent": "TEns"}, "futr": {"inner_id": "futr", "outer_id": "\u0431\u0443\u0434", "desc": "\u0431\u0443\u0434\u0443\u0449\u0435\u0435 \u0432\u0440\u0435\u043c\u044f", "parent": "TEns"}, "MOod": {"inner_id": "MOod", "outer_id": "\u041d\u0430\u043a\u043b", "desc": "\u043a\u0430\u0442\u0435\u0433\u043e\u0440\u0438\u044f \u043d\u0430\u043a\u043b\u043e\u043d\u0435\u043d\u0438\u044f", "parent": "\u2014"}, "indc": {"inner_id": "indc", "outer_id": "\u0438\u0437\u044a\u044f\u0432", "desc": "\u0438\u0437\u044a\u044f\u0432\u0438\u0442\u0435\u043b\u044c\u043d\u043e\u0435 \u043d\u0430\u043a\u043b\u043e\u043d\u0435\u043d\u0438\u0435", "parent": "MOod"}, "impr": {"inner_id": "impr", "outer_id": "\u043f\u043e\u0432\u0435\u043b", "desc": "\u043f\u043e\u0432\u0435\u043b\u0438\u0442\u0435\u043b\u044c\u043d\u043e\u0435 \u043d\u0430\u043a\u043b\u043e\u043d\u0435\u043d\u0438\u0435", "parent": "MOod"}, "INvl": {"inner_id": "INvl", "outer_id": "\u0421\u043e\u0432\u043c", "desc": "\u043a\u0430\u0442\u0435\u0433\u043e\u0440\u0438\u044f \u0441\u043e\u0432\u043c\u0435\u0441\u0442\u043d\u043e\u0441\u0442\u0438", "parent": "\u2014"}, "incl": {"inner_id": "incl", "outer_id": "\u0432\u043a\u043b", "desc": "\u0433\u043e\u0432\u043e\u0440\u044f\u0449\u0438\u0439 \u0432\u043a\u043b\u044e\u0447\u0451\u043d (\u0438\u0434\u0435\u043c, \u0438\u0434\u0435\u043c\u0442\u0435) ", "parent": "INvl"}, "excl": {"inner_id": "excl", "outer_id": "\u0432\u044b\u043a\u043b", "desc": "\u0433\u043e\u0432\u043e\u0440\u044f\u0449\u0438\u0439 \u043d\u0435 \u0432\u043a\u043b\u044e\u0447\u0451\u043d \u0432 \u0434\u0435\u0439\u0441\u0442\u0432\u0438\u0435 (\u0438\u0434\u0438, \u0438\u0434\u0438\u0442\u0435)", "parent": "INvl"}, "VOic": {"inner_id": "VOic", "outer_id": "\u0417\u0430\u043b\u043e\u0433", "desc": "\u043a\u0430\u0442\u0435\u0433\u043e\u0440\u0438\u044f \u0437\u0430\u043b\u043e\u0433\u0430", "parent": "\u2014"}, "actv": {"inner_id": "actv", "outer_id": "\u0434\u0435\u0439\u0441\u0442\u0432", "desc": "\u0434\u0435\u0439\u0441\u0442\u0432\u0438\u0442\u0435\u043b\u044c\u043d\u044b\u0439 \u0437\u0430\u043b\u043e\u0433", "parent": "VOic"}, "pssv": {"inner_id": "pssv", "outer_id": "\u0441\u0442\u0440\u0430\u0434", "desc": "\u0441\u0442\u0440\u0430\u0434\u0430\u0442\u0435\u043b\u044c\u043d\u044b\u0439 \u0437\u0430\u043b\u043e\u0433", "parent": "VOic"}, "Infr": {"inner_id": "Infr", "outer_id": "\u0440\u0430\u0437\u0433", "desc": "\u0440\u0430\u0437\u0433\u043e\u0432\u043e\u0440\u043d\u043e\u0435", "parent": "\u2014"}, "Slng": {"inner_id": "Slng", "outer_id": "\u0436\u0430\u0440\u0433", "desc": "\u0436\u0430\u0440\u0433\u043e\u043d\u043d\u043e\u0435", "parent": "\u2014"}, "Arch": {"inner_id": "Arch", "outer_id": "\u0430\u0440\u0445", "desc": "\u0443\u0441\u0442\u0430\u0440\u0435\u0432\u0448\u0435\u0435", "parent": "\u2014"}, "Litr": {"inner_id": "Litr", "outer_id": "\u043b\u0438\u0442", "desc": "\u043b\u0438\u0442\u0435\u0440\u0430\u0442\u0443\u0440\u043d\u044b\u0439 \u0432\u0430\u0440\u0438\u0430\u043d\u0442", "parent": "\u2014"}, "Erro": {"inner_id": "Erro", "outer_id": "\u043e\u043f\u0435\u0447", "desc": "\u043e\u043f\u0435\u0447\u0430\u0442\u043a\u0430", "parent": "\u2014"}, "Dist": {"inner_id": "Dist", "outer_id": "\u0438\u0441\u043a\u0430\u0436", "desc": "\u0438\u0441\u043a\u0430\u0436\u0435\u043d\u0438\u0435", "parent": "\u2014"}, "Ques": {"inner_id": "Ques", "outer_id": "\u0432\u043e\u043f\u0440", "desc": "\u0432\u043e\u043f\u0440\u043e\u0441\u0438\u0442\u0435\u043b\u044c\u043d\u043e\u0435", "parent": "\u2014"}, "Dmns": {"inner_id": "Dmns", "outer_id": "\u0443\u043a\u0430\u0437", "desc": "\u0443\u043a\u0430\u0437\u0430\u0442\u0435\u043b\u044c\u043d\u043e\u0435", "parent": "\u2014"}, "Prnt": {"inner_id": "Prnt", "outer_id": "\u0432\u0432\u043e\u0434\u043d", "desc": "\u0432\u0432\u043e\u0434\u043d\u043e\u0435 \u0441\u043b\u043e\u0432\u043e", "parent": "\u2014"}, "V-be": {"inner_id": "V-be", "outer_id": "*\u044c\u0435", "desc": "\u0444\u043e\u0440\u043c\u0430 \u043d\u0430 -\u044c\u0435", "parent": "\u2014"}, "V-en": {"inner_id": "V-en", "outer_id": "*\u0435\u043d\u0435\u043d", "desc": "\u0444\u043e\u0440\u043c\u0430 \u043d\u0430 -\u0435\u043d\u0435\u043d", "parent": "\u2014"}, "V-ie": {"inner_id": "V-ie", "outer_id": "*\u0438\u0435", "desc": "\u0444\u043e\u0440\u043c\u0430 \u043d\u0430 -\u0438- (\u0432\u0435\u0441\u0435\u043b\u0438\u0435, \u0442\u0432\u0435\u0440\u0434\u043e\u0441\u0442\u0438\u044e); \u043e\u0442\u0447\u0435\u0441\u0442\u0432\u043e \u0441 -\u0438\u0435", "parent": "\u2014"}, "V-bi": {"inner_id": "V-bi", "outer_id": "*\u044c\u0438", "desc": "\u0444\u043e\u0440\u043c\u0430 \u043d\u0430 -\u044c\u0438", "parent": "\u2014"}, "Fimp": {"inner_id": "Fimp", "outer_id": "*\u043d\u0435\u0441\u043e\u0432", "desc": "\u0434\u0435\u0435\u043f\u0440\u0438\u0447\u0430\u0441\u0442\u0438\u0435 \u043e\u0442 \u0433\u043b\u0430\u0433\u043e\u043b\u0430 \u043d\u0435\u0441\u043e\u0432\u0435\u0440\u0448\u0435\u043d\u043d\u043e\u0433\u043e \u0432\u0438\u0434\u0430", "parent": "\u2014"}, "Prdx": {"inner_id": "Prdx", "outer_id": "\u043f\u0440\u0435\u0434\u043a?", "desc": "\u043c\u043e\u0436\u0435\u0442 \u0432\u044b\u0441\u0442\u0443\u043f\u0430\u0442\u044c \u0432 \u0440\u043e\u043b\u0438 \u043f\u0440\u0435\u0434\u0438\u043a\u0430\u0442\u0438\u0432\u0430", "parent": "\u2014"}, "Coun": {"inner_id": "Coun", "outer_id": "\u0441\u0447\u0435\u0442\u043d", "desc": "\u0441\u0447\u0451\u0442\u043d\u0430\u044f \u0444\u043e\u0440\u043c\u0430", "parent": "\u2014"}, "Coll": {"inner_id": "Coll", "outer_id": "\u0441\u043e\u0431\u0438\u0440", "desc": "\u0441\u043e\u0431\u0438\u0440\u0430\u0442\u0435\u043b\u044c\u043d\u043e\u0435 \u0447\u0438\u0441\u043b\u0438\u0442\u0435\u043b\u044c\u043d\u043e\u0435", "parent": "\u2014"}, "V-sh": {"inner_id": "V-sh", "outer_id": "*\u0448\u0438", "desc": "\u0434\u0435\u0435\u043f\u0440\u0438\u0447\u0430\u0441\u0442\u0438\u0435 \u043d\u0430 -\u0448\u0438", "parent": "\u2014"}, "Af-p": {"inner_id": "Af-p", "outer_id": "*\u043f\u0440\u0435\u0434\u043b", "desc": "\u0444\u043e\u0440\u043c\u0430 \u043f\u043e\u0441\u043b\u0435 \u043f\u0440\u0435\u0434\u043b\u043e\u0433\u0430", "parent": "\u2014"}, "Inmx": {"inner_id": "Inmx", "outer_id": "\u043d\u0435/\u043e\u0434\u0443\u0448?", "desc": "\u043c\u043e\u0436\u0435\u0442 \u0438\u0441\u043f\u043e\u043b\u044c\u0437\u043e\u0432\u0430\u0442\u044c\u0441\u044f \u043a\u0430\u043a \u043e\u0434\u0443\u0448. / \u043d\u0435\u043e\u0434\u0443\u0448. ", "parent": "\u2014"}, "Vpre": {"inner_id": "Vpre", "outer_id": "\u0432_\u043f\u0440\u0435\u0434\u043b", "desc": "\u0412\u0430\u0440\u0438\u0430\u043d\u0442 \u043f\u0440\u0435\u0434\u043b\u043e\u0433\u0430 ( \u0441\u043e, \u043f\u043e\u0434\u043e, ...)", "parent": "\u2014"}, "Anph": {"inner_id": "Anph", "outer_id": "\u0430\u043d\u0430\u0444", "desc": "\u0410\u043d\u0430\u0444\u043e\u0440\u0438\u0447\u0435\u0441\u043a\u043e\u0435 (\u043c\u0435\u0441\u0442\u043e\u0438\u043c\u0435\u043d\u0438\u0435)", "parent": "\u2014"}, "Init": {"inner_id": "Init", "outer_id": "\u0438\u043d\u0438\u0446", "desc": "\u0418\u043d\u0438\u0446\u0438\u0430\u043b", "parent": "\u2014"}, "Adjx": {"inner_id": "Adjx", "outer_id": "\u043f\u0440\u0438\u043b?", "desc": "\u043c\u043e\u0436\u0435\u0442 \u0432\u044b\u0441\u0442\u0443\u043f\u0430\u0442\u044c \u0432 \u0440\u043e\u043b\u0438 \u043f\u0440\u0438\u043b\u0430\u0433\u0430\u0442\u0435\u043b\u044c\u043d\u043e\u0433\u043e", "parent": "\u2014"}, "Ms-f": {"inner_id": "Ms-f", "outer_id": "\u043e\u0440", "desc": "\u043a\u043e\u043b\u0435\u0431\u0430\u043d\u0438\u0435 \u043f\u043e \u0440\u043e\u0434\u0443 (\u043c/\u0436/\u0441): \u043a\u043e\u0444\u0435, \u0432\u043e\u043b\u044c\u0432\u043e", "parent": "\u2014"}, "Hypo": {"inner_id": "Hypo", "outer_id": "\u0433\u0438\u043f\u043e\u0442", "desc": "\u0433\u0438\u043f\u043e\u0442\u0435\u0442\u0438\u0447\u0435\u0441\u043a\u0430\u044f \u0444\u043e\u0440\u043c\u0430 \u0441\u043b\u043e\u0432\u0430 (\u043f\u043e\u0431\u0435\u0434\u044e, \u0430\u0441\u0444\u0430\u043b\u044c\u0442\u043e\u0432\u0435\u0435)", "parent": "\u2014"}}